Flask_WTF_Decorators-0.1.2.dist-info/LICENSE.txt
Flask_WTF_Decorators-0.1.2.dist-info/METADATA
Flask_WTF_Decorators-0.1.2.dist-info/RECORD
Flask_WTF_Decorators-0.1.2.dist-info/WHEEL
Flask_WTF_Decorators-0.1.2.dist-info/top_level.txt
flask_wtf_decorators/__init__.py
